k4sprofff.py
k4sprofff-1.0.dist-info/METADATA
k4sprofff-1.0.dist-info/WHEEL
k4sprofff-1.0.dist-info/top_level.txt
k4sprofff-1.0.dist-info/RECORD
