Metadata-Version: 2.1
Name: k4sprofff
Version: 1.0
Summary: for profile
Home-page: https://github.com/upuuuuuu
Author: upuuuuuu
Author-email: 2226548059@qq.com
License: MIT
Requires: os
Requires: time
Requires: torch
Requires: logging
Requires: pandas
Requires: torchstat
